myvodapi/__init__.py
myvodapi/core.py
myvodapi-0.0.2.dist-info/METADATA
myvodapi-0.0.2.dist-info/WHEEL
myvodapi-0.0.2.dist-info/top_level.txt
myvodapi-0.0.2.dist-info/RECORD
