Metadata-Version: 2.1
Name: myvodapi
Version: 0.0.2
Summary: my.vodafone.ua api wrapper, written on python.
Home-page: https://github.com/Vezono/myvodapi
Author: Vezono
Author-email: gbball.baas@gmail.com
License: UNKNOWN
Platform: UNKNOWN
Classifier: Programming Language :: Python :: 3
Classifier: License :: OSI Approved :: MIT License
Classifier: Operating System :: OS Independent
Requires-Python: >=3.6
